LICENSE
README.md
setup.py
promexp/__init__.py
promexp/metrics.py
promexp/provider.py
promexp.egg-info/PKG-INFO
promexp.egg-info/SOURCES.txt
promexp.egg-info/dependency_links.txt
promexp.egg-info/top_level.txt
promexp/providers/__init__.py
promexp/providers/network.py
promexp/providers/nvidia.py
promexp/providers/psutil.py
promexp/providers/storage.py
promexp/providers/storagespaces.py
promexp/providers/casparcg/__init__.py
promexp/providers/casparcg/bundle.py
promexp/providers/casparcg/message.py
promexp/providers/casparcg/ntp.py
promexp/providers/casparcg/osc_server.py
promexp/providers/casparcg/osc_types.py
promexp/providers/casparcg/packet.py