Metadata-Version: 2.1
Name: promexp
Version: 1.0.3
Summary: A simple system metrics exporter for Prometheus
Home-page: https://github.com/immstudios/promexp
Author: Martin Wacker
Author-email: martas@imm.cz
License: MIT
Keywords: metrics devops prometheus
Platform: UNKNOWN
Classifier: Development Status :: 5 - Production/Stable
Classifier: Environment :: Console
Classifier: Intended Audience :: Developers
Classifier: License :: OSI Approved :: MIT License
Classifier: Natural Language :: English
Classifier: Operating System :: POSIX :: Linux
Classifier: Programming Language :: Python
Classifier: Topic :: Utilities
License-File: LICENSE
